MANIFEST.in
README.rst
VERSION
setup.py
./srange/__init__.py
./srange/srange.py
./srange/symrange.py
srange/LICENSE.txt
srange.egg-info/PKG-INFO
srange.egg-info/SOURCES.txt
srange.egg-info/dependency_links.txt
srange.egg-info/top_level.txt